stowage/__init__.py
stowage/stowage.py
stowage-0.1.9.dist-info/DESCRIPTION.rst
stowage-0.1.9.dist-info/METADATA
stowage-0.1.9.dist-info/RECORD
stowage-0.1.9.dist-info/WHEEL
stowage-0.1.9.dist-info/entry_points.txt
stowage-0.1.9.dist-info/metadata.json
stowage-0.1.9.dist-info/top_level.txt
